lsp/config.yml
databricks/__init__.py
databricks/labs/__init__.py
databricks/labs/bladebridge/__about__.py
databricks/labs/bladebridge/__init__.py
databricks/labs/bladebridge/aggregator.py
databricks/labs/bladebridge/helpers.py
databricks/labs/bladebridge/logger.py
databricks/labs/bladebridge/lsp_extension.py
databricks/labs/bladebridge/server.py
databricks/labs/bladebridge/transpiler.py
databricks/labs/bladebridge/Converter/Configs/README.txt
databricks/labs/bladebridge/Converter/Configs/tech_mapper_main.json
databricks/labs/bladebridge/Converter/Configs/DatabricksWorkflow/ASSIGNMENT_template.py
databricks/labs/bladebridge/Converter/Configs/DatabricksWorkflow/CONTROL_template.py
databricks/labs/bladebridge/Converter/Configs/DatabricksWorkflow/DECISION_template.py
databricks/labs/bladebridge/Converter/Configs/DatabricksWorkflow/EMAIL_template.py
databricks/labs/bladebridge/Converter/Configs/DatabricksWorkflow/NESTED_CONDITION_template.py
databricks/labs/bladebridge/Converter/Configs/DatabricksWorkflow/START_template.py
databricks/labs/bladebridge/Converter/Configs/DatabricksWorkflow/databricksJobs_template_COMMAND.py
databricks/labs/bladebridge/Converter/Configs/DatabricksWorkflow/databricksJobs_template_DIE.py
databricks/labs/bladebridge/Converter/Configs/DatabricksWorkflow/databricksJobs_template_EMPTY_COMMAND.py
databricks/labs/bladebridge/Converter/Configs/DatabricksWorkflow/databricksJobs_template_EXCEPTION_HANDLER.py
databricks/labs/bladebridge/Converter/Configs/DatabricksWorkflow/databricksJobs_template_FORK.py
databricks/labs/bladebridge/Converter/Configs/DatabricksWorkflow/databricksJobs_template_JOIN.py
databricks/labs/bladebridge/Converter/Configs/DatabricksWorkflow/databricksJobs_template_LOOKUP.py
databricks/labs/bladebridge/Converter/Configs/DatabricksWorkflow/databricksJobs_template_LOOP_START.py
databricks/labs/bladebridge/Converter/Configs/DatabricksWorkflow/databricksJobs_template_NESTED_CONDITION.py
databricks_bb_plugin-0.2.0.dist-info/METADATA
databricks_bb_plugin-0.2.0.dist-info/WHEEL
databricks_bb_plugin-0.2.0.dist-info/RECORD
