Metadata-Version: 2.4
Name: databricks-bb-plugin
Version: 0.2.0
Summary: Bladebridge transpiler plugin
Project-URL: Documentation, https://github.com/databrickslabs/bladerunner
Project-URL: Issues, https://github.com/databrickslabs/bladerunner/issues
Project-URL: Source, https://github.com/databrickslabs/bladerunner
Keywords: Bladebridge,Databricks,Transpiler
Classifier: Development Status :: 3 - Alpha
Classifier: Programming Language :: Python :: 3.10
Classifier: Programming Language :: Python :: Implementation :: CPython
Requires-Python: >=3.10
Requires-Dist: databricks-labs-blueprint<0.12.0,>=0.11.3
Requires-Dist: psutil>=7.0.0
Requires-Dist: pygls>=2.0.0
Requires-Dist: pyyaml>=6.0.2
